{
  "plugins": {
    "LuaSnip": {
      "rev": "3732756",
      "src": "https://github.com/L3MON4D3/LuaSnip"
    },
    "blink.cmp": {
      "rev": "7beba91fdc61fdc84ea6d6395d614671e609f895",
      "src": "https://github.com/saghen/blink.cmp"
    },
    "bufferline.nvim": {
      "rev": "655133c",
      "src": "https://github.com/akinsho/bufferline.nvim"
    },
    "conform.nvim": {
      "rev": "4993e07",
      "src": "https://github.com/stevearc/conform.nvim"
    },
    "dropbar.nvim": {
      "rev": "ce20224",
      "src": "https://github.com/Bekaboo/dropbar.nvim"
    },
    "flash.nvim": {
      "rev": "fcea7ff",
      "src": "https://github.com/folke/flash.nvim"
    },
    "gitsigns.nvim": {
      "rev": "5813e4878748805f1518cee7abb50fd7205a3a48",
      "src": "https://github.com/lewis6991/gitsigns.nvim"
    },
    "ibl": {
      "rev": "005b560",
      "src": "https://github.com/lukas-reineke/indent-blankline.nvim"
    },
    "lazydev.nvim": {
      "rev": "5231c62",
      "src": "https://github.com/folke/lazydev.nvim"
    },
    "lualine.nvim": {
      "rev": "47f91c4",
      "src": "https://github.com/nvim-lualine/lualine.nvim"
    },
    "marks.nvim": {
      "rev": "f353e8c",
      "src": "https://github.com/chentoast/marks.nvim"
    },
    "mason-tool-installer.nvim": {
      "rev": "517ef59",
      "src": "https://github.com/WhoIsSethDaniel/mason-tool-installer.nvim"
    },
    "mason.nvim": {
      "rev": "57e5a8a",
      "src": "https://github.com/williamboman/mason.nvim"
    },
    "mini.ai": {
      "rev": "bfb26d9",
      "src": "https://github.com/nvim-mini/mini.ai"
    },
    "mini.icons": {
      "rev": "ff2e4f1d29f659cc2bad0f9256f2f6195c6b2428",
      "src": "https://github.com/nvim-mini/mini.icons"
    },
    "mini.surround": {
      "rev": "88c5229",
      "src": "https://github.com/nvim-mini/mini.surround"
    },
    "nvim-dap": {
      "rev": "5860c7c",
      "src": "https://codeberg.org/mfussenegger/nvim-dap.git"
    },
    "nvim-dap-python": {
      "rev": "64652d1",
      "src": "https://github.com/mfussenegger/nvim-dap-python"
    },
    "nvim-dap-ui": {
      "rev": "cf91d5e",
      "src": "https://github.com/rcarriga/nvim-dap-ui"
    },
    "nvim-dap-virtual-text": {
      "rev": "fbdb48c",
      "src": "https://github.com/theHamsta/nvim-dap-virtual-text"
    },
    "nvim-lspconfig": {
      "rev": "effe4bf2e1afb881ea67291c648b68dd3dfc927a",
      "src": "https://github.com/neovim/nvim-lspconfig"
    },
    "nvim-nio": {
      "rev": "21f5324",
      "src": "https://github.com/nvim-neotest/nvim-nio"
    },
    "nvim-treesitter": {
      "rev": "c5623d3486c1cda5f73e28a3a4abb454f708c48c",
      "src": "https://github.com/nvim-treesitter/nvim-treesitter",
      "version": "'main'"
    },
    "nvim-treesitter-textobjects": {
      "rev": "dfbf9596f8aa8b4bed5301647485594ff7252955",
      "src": "https://github.com/nvim-treesitter/nvim-treesitter-textobjects",
      "version": "'main'"
    },
    "nvim-web-devicons": {
      "rev": "8dcb311",
      "src": "https://github.com/nvim-tree/nvim-web-devicons"
    },
    "oil.nvim": {
      "rev": "cbcb3f997f6f261c577b943ec94e4ef55108dd95",
      "src": "https://github.com/stevearc/oil.nvim"
    },
    "persistence.nvim": {
      "rev": "b20b2a7",
      "src": "https://github.com/folke/persistence.nvim"
    },
    "plenary.nvim": {
      "rev": "b9fd522",
      "src": "https://github.com/nvim-lua/plenary.nvim"
    },
    "rose-pine": {
      "rev": "cf2a288",
      "src": "https://github.com/rose-pine/neovim"
    },
    "snacks.nvim": {
      "rev": "fe7cfe9",
      "src": "https://github.com/folke/snacks.nvim"
    },
    "typst-preview.nvim": {
      "rev": "291972a39db85c5d2e76249748aba4206dfd3bc2",
      "src": "https://github.com/chomosuke/typst-preview.nvim"
    },
    "vim-slime": {
      "rev": "67b24bf",
      "src": "https://github.com/jpalardy/vim-slime"
    },
    "which-key.nvim": {
      "rev": "3aab214",
      "src": "https://github.com/folke/which-key.nvim"
    },
    "yazi.nvim": {
      "rev": "7ffb707ab34d425486eee0ae195546c25e05bf42",
      "src": "https://github.com/mikavilpas/yazi.nvim"
    }
  }
}